setup.py
banish/__init__.py
banish/admin.py
banish/middleware.py
banish/models.py
django_banish.egg-info/PKG-INFO
django_banish.egg-info/SOURCES.txt
django_banish.egg-info/dependency_links.txt
django_banish.egg-info/requires.txt
django_banish.egg-info/top_level.txt