Metadata-Version: 1.1
Name: django-banish
Version: 0.2
Summary: django middleware to ban users, prevent too many concurrent connections
Home-page: http://github.com/yourabi/django-banish
Author: Yousef Ourabi
Author-email: yourabi@gmail.com
License: Apache
Platform: Posix; MacOS X;
Classifier: Intended Audience :: Developers
Classifier: License :: OSI Approved :: Apache Software License
Classifier: Topic :: Internet :: WWW/HTTP
Classifier: Topic :: Software Development :: Libraries :: Application Frameworks
Classifier: Topic :: Software Development :: Libraries :: Python Modules
